{"stat.chestOpened":3,"stat.walkOneCm":82727,"stat.playerKills":2,"achievement.openInventory":17,"stat.useItem.minecraft.stone":4,"stat.leaveGame":4,"stat.mobKills":1,"stat.useItem.minecraft.diamond_sword":9,"stat.flyOneCm":268576,"stat.deaths":9,"stat.drop":7,"stat.jump":42,"stat.swimOneCm":88,"stat.playOneMinute":126404,"stat.climbOneCm":3674,"stat.damageDealt":910,"stat.crouchOneCm":23592,"stat.enderchestOpened":1,"stat.timeSinceDeath":5216,"stat.sprintOneCm":2247,"achievement.exploreAllBiomes":{"value":0,"progress":["Savanna Plateau","DesertHills","Forest","River","Plains","Taiga","Desert","Extreme Hills","TaigaHills","Savanna"]},"stat.diveOneCm":449}